__init__.py
mlpython/__init__.py
mlpython/datasets/__init__.py
mlpython/datasets/abalone.py
mlpython/datasets/adult.py
mlpython/datasets/bibtex.py
mlpython/datasets/binarized_mnist.py
mlpython/datasets/cadata.py
mlpython/datasets/cifar10.py
mlpython/datasets/connect4.py
mlpython/datasets/convex.py
mlpython/datasets/corel5k.py
mlpython/datasets/corrupted_mnist.py
mlpython/datasets/corrupted_ocr_letters.py
mlpython/datasets/dna.py
mlpython/datasets/face_completion_lfw.py
mlpython/datasets/heart.py
mlpython/datasets/housing.py
mlpython/datasets/letor_mq2007.py
mlpython/datasets/letor_mq2008.py
mlpython/datasets/majmin.py
mlpython/datasets/mediamill.py
mlpython/datasets/medical.py
mlpython/datasets/mnist.py
mlpython/datasets/mnist_background_images.py
mlpython/datasets/mnist_background_random.py
mlpython/datasets/mnist_basic.py
mlpython/datasets/mnist_rotated.py
mlpython/datasets/mnist_rotated_background_images.py
mlpython/datasets/mturk.py
mlpython/datasets/mushrooms.py
mlpython/datasets/newsgroups.py
mlpython/datasets/nips.py
mlpython/datasets/occluded_faces_lfw.py
mlpython/datasets/occluded_mnist.py
mlpython/datasets/ocr_letters.py
mlpython/datasets/rcv1.py
mlpython/datasets/rectangles.py
mlpython/datasets/rectangles_images.py
mlpython/datasets/reuters_v1.py
mlpython/datasets/sarcos.py
mlpython/datasets/scene.py
mlpython/datasets/store.py
mlpython/datasets/web.py
mlpython/datasets/yahoo_ltrc1.py
mlpython/datasets/yahoo_ltrc2.py
mlpython/datasets/yeast.py
mlpython/doc/__init__.py
mlpython/doc/conf.py
mlpython/learners/__init__.py
mlpython/learners/classification.py
mlpython/learners/distribution.py
mlpython/learners/dynamic.py
mlpython/learners/features.py
mlpython/learners/generic.py
mlpython/learners/multilabel.py
mlpython/learners/ranking.py
mlpython/learners/sparse/__init__.py
mlpython/learners/sparse/classification.py
mlpython/learners/third_party/__init__.py
mlpython-0.1.3.dist-info/DESCRIPTION.rst
mlpython-0.1.3.dist-info/METADATA
mlpython-0.1.3.dist-info/RECORD
mlpython-0.1.3.dist-info/WHEEL
mlpython-0.1.3.dist-info/metadata.json
mlpython-0.1.3.dist-info/top_level.txt
