Metadata-Version: 2.0
Name: mlpython
Version: 0.1.3
Summary: Small ML library for loading standard ML datasets and models
Home-page: https://github.com/AmirHooshangi/mlpython
Author: Hugo Larochelle
Author-email: hugo.larochelle@usherbrooke.ca 
License: GPL
Platform: UNKNOWN
